cfn_guard_rs_hook/__init__.py
cfn_guard_rs_hook/guard_hook.py
cfn_guard_rs_hook/types.py
cfn_guard_rs_hook-0.3.3.dist-info/METADATA
cfn_guard_rs_hook-0.3.3.dist-info/WHEEL
cfn_guard_rs_hook-0.3.3.dist-info/RECORD
